work_wechat/__init__.py
WorkWeChatSDK-20200430.dist-info/LICENSE
WorkWeChatSDK-20200430.dist-info/METADATA
WorkWeChatSDK-20200430.dist-info/WHEEL
WorkWeChatSDK-20200430.dist-info/top_level.txt
WorkWeChatSDK-20200430.dist-info/RECORD
